filepond/__init__.py
filepond/apps.py
filepond/forms.py
filepond/middleware.py
filepond/models.py
filepond/runner.py
filepond/urls.py
filepond/utils.py
filepond/views.py
filepond/migrations/0001_initial.py
filepond/migrations/0002_auto_20181127_0925.py
filepond/migrations/0003_auto_20181127_0938.py
filepond/migrations/__init__.py
filepond/static/css/filepond.css
filepond/static/img/.gitignore
filepond/static/js/filepond.js
filepond/templates/upload_form.html
filepond/templates/filepond/base.html
filepond/templates/filepond/upload_form.html
django_filepond-0.1.4.dist-info/LICENSE
django_filepond-0.1.4.dist-info/WHEEL
django_filepond-0.1.4.dist-info/METADATA
django_filepond-0.1.4.dist-info/RECORD
